Workbook

Sheet Notes
A1: Greggs three-statement forecast model – Notes
A2: GRG_model_v0.3 · v0.1 shell and historicals (9 Oct 2026); v0.2 Tax & Audit tab (10 Oct); v0.3 Session B assumptions and full forecast except revenue (11 Oct) · save a new version each session
A4: NEXT STEP | B4: Session C: build the revenue section on the Revenue tab (yellow cells). Then check the Checks tab: the balance sheet and cash checks should read 0 for FY26–FY28.
A6: Colour key
A7: Blue text | B7: Typed input from a report or your own assumption
A8: Black text | B8: Formula on the same sheet
A9: Green text | B9: Link to another sheet
A10: Yellow fill | B10: Cell you still need to fill in
A11: Grey fill | B11: Forecast cell to build in Phase 2
A14: Tabs
A15: Historical | B15: FY21–FY25 statements, revenue split, shop KPIs, with page references. Filled.
A16: Revenue | B16: Session C: company-managed shop roll-forward and B2B revenue, built by Siddharth.
A17: Forecast | B17: Same rows; FY21–FY25 linked; FY26–FY28 formulas driven by Drivers and Revenue, with schedules at the bottom.
A18: Drivers | B18: Session B assumptions with Monte Carlo ranges, approved defaults, historical reference ratios, H1 2026 guidance.
A19: Scenarios | B19: Switch cell and base/upside/downside table (Phase 3).
A20: Variance | B20: FY25 back-test and FY26 live-test layouts; actual FY25 already linked.
A21: Tax & Audit | B21: Phase 3: tax rate reconciliation, deferred tax roll-forward, key audit matters map, model controls.
A22: Checks | B22: Ties every historical total to the reports; balance and cash checks for the forecast.
A23: Summary | B23: Headings for the one-page summary (Phase 3).
A25: Source files (put these in 01_Sources)
A26: AR21 | B26: Greggs Annual Report and Accounts 2021 (52 weeks to 1 Jan 2022)
A27: AR22 | B27: Annual Report 2022 (52 weeks to 31 Dec 2022): used for FY21 figures
A28: AR23 | B28: Annual Report and Accounts 2023 (52 weeks to 30 Dec 2023): used for FY22 figures
A29: AR24 | B29: Annual Report and Accounts 2024 (52 weeks to 28 Dec 2024): used for FY23 figures
A30: AR25 | B30: Annual Report and Accounts 2025 (52 weeks to 27 Dec 2025): used for FY24 and FY25 figures
A31: H1 2026 | B31: Interim results presentation, 29 Jul 2026 (26 weeks to 27 Jun 2026)
A32: Rule | B32: Each year is taken from the following year's report where possible, so restated comparatives are used. Page numbers are PDF pages (printed page = PDF page minus 2).
A35: Simplifications and presentation choices already made
A36: 1. | B36: Interest received is shown in operating cash flow for all years (Greggs' FY25 policy). FY22 and FY23 operating/investing subtotals therefore differ from those reports by 1.4 and 6.1; net change in cash is unchanged.
A37: 2. | B37: FY21 and FY22 finance income and expense are split using the finance note; the face of the income statement only showed a net figure.
A38: 3. | B38: Distribution, admin and other income are statutory totals (including exceptional items). Underlying profit is derived by stripping the exceptional rows.
A39: 4. | B39: Parent company figures are ignored; all figures are Group.
A40: 5. | B40: FY21 is distorted by Covid (LFL +52.4% vs 2020). Consider basing ratios on FY22–FY25 and saying so.
A43: Open questions to resolve
A44: Q1 | B44: FY25 franchised shop count, gross openings and closures: not in the report text. Look in the FY25 results announcement (early March 2026) on Greggs' investor site.
A45: Q2 | B45: FY21 franchised count (375) was stated as 'currently' in a report published in early 2022, so it is approximate.
A46: Q3 | B46: ANSWERED (10 Oct 2026): FY26 is a 52-week year to 26 Dec 2026, confirmed by Siddharth. No 53rd-week adjustment.
A47: Q4 | B47: Date of the January 2027 trading update (for the locked forecast in Phase 4).
A50: Assumptions log (fill in during Phase 2)
A51: Assumption | B51: Value | C51: Years | D51: Reason and source | E51: Date set
A52: Example: company-managed LFL growth | B52: 0.025 | C52: FY26 | D52: H1 2026 LFL 2.1%, Q3 c.3.4%; weighted toward recent trend | E52: Nov 2026
A53: (Example row in grey: replace it with your own)

Sheet Historical
A1: Greggs plc – historical financials, FY21–FY25
A2: £m unless stated. Blue = typed from the reports (check each one); black = formula. Page numbers are PDF pages of the annual reports (AR21 = Annual Report 2021, etc.).
A3: Status: extracted by Claude on 9 Oct 2026. Not yet checked by Siddharth. Tick 'Checked' on the Checks sheet as you verify each statement.
A4: £m | B4: Source (PDF page) | C4: FY21 | D4: FY22 | E4: FY23 | F4: FY24 | G4: FY25
A5: Period end (weeks) | C5: 1 Jan 2022 (52) | D5: 31 Dec 2022 (52) | E5: 30 Dec 2023 (52) | F5: 28 Dec 2024 (52) | G5: 27 Dec 2025 (52)
A6: INCOME STATEMENT (statutory, including exceptional items)
A7: Revenue | B7: IS: FY24–25 AR25 p130; FY23 AR24 p130; FY22 AR23 p121; FY21 AR22 p110 | C7: 1229.7 | D7: 1512.8 | E7: 1809.6 | F7: 2014.4 | G7: 2151.2
A8: Cost of sales | B8: IS: FY24–25 AR25 p130; FY23 AR24 p130; FY22 AR23 p121; FY21 AR22 p110 | C8: -447.7 | D8: -574.5 | E8: -710.5 | F8: -770.8 | G8: -829.1
A9: Gross profit | B9: Formula | C9: =C7+C8 -> 782 | D9: =D7+D8 -> 938.3 | E9: =E7+E8 -> 1099.1 | F9: =F7+F8 -> 1243.6 | G9: =G7+G8 -> 1322.1
A10: Distribution and selling costs | B10: IS: FY24–25 AR25 p130; FY23 AR24 p130; FY22 AR23 p121; FY21 AR22 p110 | C10: -567.6 | D10: -713.2 | E10: -844.2 | F10: -950.1 | G10: -1036.3
A11: Administrative expenses | B11: IS: FY24–25 AR25 p130; FY23 AR24 p130; FY22 AR23 p121; FY21 AR22 p110 | C11: -61.2 | D11: -70.7 | E11: -82.9 | F11: -97.9 | G11: -102.1
A12: Other income (exceptional) | B12: IS: FY24–25 AR25 p130; FY23 AR24 p130; FY22 AR23 p121; FY21 AR22 p110 | C12: 0 | D12: 0 | E12: 20.3 | F12: 13.8 | G12: 0
A13: Operating profit | B13: Formula | C13: =C9+C10+C11+C12 -> 153.2 | D13: =D9+D10+D11+D12 -> 154.4 | E13: =E9+E10+E11+E12 -> 192.3 | F13: =F9+F10+F11+F12 -> 209.4 | G13: =G9+G10+G11+G12 -> 183.7
A14: Finance income | B14: FY21 AR22 p131 (note 5); FY22 AR23 p142 (note 6); FY23–25 IS | C14: 0 | D14: 1.4 | E14: 6.1 | F14: 8.1 | G14: 1.8
A15: Finance expense | B15: FY21 AR22 p131 (note 5); FY22 AR23 p142 (note 6); FY23–25 IS | C15: -7.6 | D15: -7.5 | E15: -10.1 | F15: -13.6 | G15: -18.1
A16: Profit before tax | B16: Formula | C16: =C13+C14+C15 -> 145.6 | D16: =D13+D14+D15 -> 148.3 | E16: =E13+E14+E15 -> 188.3 | F16: =F13+F14+F15 -> 203.9 | G16: =G13+G14+G15 -> 167.4
A17: Income tax | B17: IS: FY24–25 AR25 p130; FY23 AR24 p130; FY22 AR23 p121; FY21 AR22 p110 | C17: -28.1 | D17: -28 | E17: -45.8 | F17: -50.5 | G17: -45.2
A18: Profit for the year | B18: Formula | C18: =C16+C17 -> 117.5 | D18: =D16+D17 -> 120.3 | E18: =E16+E17 -> 142.5 | F18: =F16+F17 -> 153.4 | G18: =G16+G17 -> 122.2
A20: Exceptional items and underlying profit
A21: Exceptional items within operating profit | B21: IS exceptional column | C21: 0 | D21: 0 | E21: 20.6 | F21: 14.1 | G21: -3.8
A22: Exceptional items within finance expense | B22: AR25 p130 | C22: 0 | D22: 0 | E22: 0 | F22: 0 | G22: -0.7
A23: Tax on exceptional items | B23: IS exceptional column | C23: 0 | D23: 0 | E23: -4.8 | F23: -1.7 | G23: 0.9
A24: Underlying operating profit | B24: Formula | C24: =C13-C21 -> 153.2 | D24: =D13-D21 -> 154.4 | E24: =E13-E21 -> 171.7 | F24: =F13-F21 -> 195.3 | G24: =G13-G21 -> 187.5
A25: Underlying profit before tax | B25: Formula | C25: =C16-C21-C22 -> 145.6 | D25: =D16-D21-D22 -> 148.3 | E25: =E16-E21-E22 -> 167.7 | F25: =F16-F21-F22 -> 189.8 | G25: =G16-G21-G22 -> 171.9
A26: Underlying operating margin | B26: Formula | C26: =IF(C7=0,0,C24/C7) -> 0.12458323 | D26: =IF(D7=0,0,D24/D7) -> 0.1020624 | E26: =IF(E7=0,0,E24/E7) -> 0.094882847 | F26: =IF(F7=0,0,F24/F7) -> 0.096951946 | G26: =IF(G7=0,0,G24/G7) -> 0.087160655
A27: Effective tax rate (statutory) | B27: Formula | C27: =IF(C16=0,0,-C17/C16) -> 0.19299451 | D27: =IF(D16=0,0,-D17/D16) -> 0.18880647 | E27: =IF(E16=0,0,-E17/E16) -> 0.24322889 | F27: =IF(F16=0,0,-F17/F16) -> 0.24767043 | G27: =IF(G16=0,0,-G17/G16) -> 0.27001195
A29: Reported totals (typed from the reports, for the checks)
A30: Reported operating profit | B30: IS: FY24–25 AR25 p130; FY23 AR24 p130; FY22 AR23 p121; FY21 AR22 p110 | C30: 153.2 | D30: 154.4 | E30: 192.3 | F30: 209.4 | G30: 183.7
A31: Reported profit before tax | B31: IS: FY24–25 AR25 p130; FY23 AR24 p130; FY22 AR23 p121; FY21 AR22 p110 | C31: 145.6 | D31: 148.3 | E31: 188.3 | F31: 203.9 | G31: 167.4
A32: Reported profit for the year | B32: IS: FY24–25 AR25 p130; FY23 AR24 p130; FY22 AR23 p121; FY21 AR22 p110 | C32: 117.5 | D32: 120.3 | E32: 142.5 | F32: 153.4 | G32: 122.2
A33: Reported underlying PBT | B33: AR25 p176 (ten-year history) | C33: 145.6 | D33: 148.3 | E33: 167.7 | F33: 189.8 | G33: 171.9
A35: REVENUE SPLIT AND SHOP KPIs
A36: Revenue: company-managed shops | B36: FY21 AR22 p126; FY22 AR23 p137; FY23 AR24 p175; FY24–25 AR25 p177 | C36: 1098.2 | D36: 1352.3 | E36: 1610.9 | F36: 1781.7 | G36: 1897.2
A37: Revenue: business to business (franchise, wholesale, grocery) | B37: FY21 AR22 p126; FY22 AR23 p137; FY23 AR24 p175; FY24–25 AR25 p177 | C37: 131.5 | D37: 160.5 | E37: 198.7 | F37: 232.7 | G37: 254
A38: Check: split less revenue (should be 0) | B38: Formula | C38: =C36+C37-C7 -> 0 | D38: =D36+D37-D7 -> 0 | E38: =E36+E37-E7 -> 0 | F38: =F36+F37-F7 -> 0 | G38: =G36+G37-G7 -> 0
A39: Shops at start of year | B39: FY20 closing: AR25 p176 | C39: 2078 | D39: =C40 -> 2181 | E39: =D40 -> 2328 | F39: =E40 -> 2473 | G39: =F40 -> 2618
A40: Shops at year end (total) | B40: AR25 p176 (ten-year history) | C40: 2181 | D40: 2328 | E40: 2473 | F40: 2618 | G40: 2739
A41: of which franchised | B41: FY21 AR21 p18; FY22 AR22 p15; FY23 AR23 p17; FY24 AR24 p33; FY25 Q4 trading update 8 Jan 2026 | C41: 375 | D41: 441 | E41: 503 | F41: 561 | G41: 602
A42: of which company-managed | B42: Formula | C42: =IF(C41="","",C40-C41) -> 1806 | D42: =IF(D41="","",D40-D41) -> 1887 | E42: =IF(E41="","",E40-E41) -> 1970 | F42: =IF(F41="","",F40-F41) -> 2057 | G42: =IF(G41="","",G40-G41) -> 2137
A43: Gross openings | B43: FY21 AR21 p18; FY22 AR22 p15; FY23 AR23 p17; FY24 AR24 p22; FY25 Q4 trading update 8 Jan 2026 | C43: 131 | D43: 186 | E43: 220 | F43: 226 | G43: 207
A44: Closures (incl. relocations) | B44: FY21 AR21 p18; FY22 AR22 p15; FY23 derived; FY24 AR24 p22; FY25 Q4 trading update | C44: -28 | D44: -39 | E44: -75 | F44: -81 | G44: -86
A45: Net openings | B45: Formula | C45: =C40-C39 -> 103 | D45: =D40-D39 -> 147 | E45: =E40-E39 -> 145 | F45: =F40-F39 -> 145 | G45: =G40-G39 -> 121
A46: Check: openings + closures less net (should be 0) | B46: Formula | C46: =IF(C43="",0,C43+C44-C45) -> 0 | D46: =IF(D43="",0,D43+D44-D45) -> 0 | E46: =IF(E43="",0,E43+E44-E45) -> 0 | F46: =IF(F43="",0,F43+F44-F45) -> 0 | G46: =IF(G43="",0,G43+G44-G45) -> 0
A47: Company-managed like-for-like sales growth | B47: AR25 p176 (ten-year history) | C47: 0.524 | D47: 0.178 | E47: 0.137 | F47: 0.055 | G47: 0.024
A48: Franchise like-for-like system sales growth | B48: FY23 AR24 p175; FY24–25 AR25 p177 | E48: 0.149 | F48: 0.074 | G48: 0.043
A49: Company-managed revenue per average shop (£m) | B49: Formula | C49: =IF(C42="","",C36/C42) -> 0.60808416 | D49: =IF(D42="","",D36/AVERAGE(D42,IF(C42="",D42,C42))) -> 0.73235852 | E49: =IF(E42="","",E36/AVERAGE(E42,IF(D42="",E42,D42))) -> 0.83531242 | F49: =IF(F42="","",F36/AVERAGE(F42,IF(E42="",F42,E42))) -> 0.88487708 | G49: =IF(G42="","",G36/AVERAGE(G42,IF(F42="",G42,F42))) -> 0.90472103
A51: BALANCE SHEET (group)
A52: Intangible assets | B52: BS: FY24–25 AR25 p131; FY23 AR24 p131; FY22 AR23 p122; FY21 AR22 p111 | C52: 14.9 | D52: 13.5 | E52: 18.3 | F52: 24.9 | G52: 43
A53: Property, plant and equipment | B53: BS: FY24–25 AR25 p131; FY23 AR24 p131; FY22 AR23 p122; FY21 AR22 p111 | C53: 343.8 | D53: 390 | E53: 510.3 | F53: 664.7 | G53: 832.1
A54: Right-of-use assets | B54: BS: FY24–25 AR25 p131; FY23 AR24 p131; FY22 AR23 p122; FY21 AR22 p111 | C54: 263.6 | D54: 281.6 | E54: 296.6 | F54: 387.2 | G54: 413
A55: Defined benefit pension asset | B55: BS: FY24–25 AR25 p131; FY23 AR24 p131; FY22 AR23 p122; FY21 AR22 p111 | C55: 0 | D55: 6.3 | E55: 6.6 | F55: 0 | G55: 0
A56: Non-current assets | B56: Formula | C56: =SUM(C52:C55) -> 622.3 | D56: =SUM(D52:D55) -> 691.4 | E56: =SUM(E52:E55) -> 831.8 | F56: =SUM(F52:F55) -> 1076.8 | G56: =SUM(G52:G55) -> 1288.1
A57: Inventories | B57: BS: FY24–25 AR25 p131; FY23 AR24 p131; FY22 AR23 p122; FY21 AR22 p111 | C57: 27.9 | D57: 40.6 | E57: 48.8 | F57: 55.2 | G57: 55.7
A58: Trade and other receivables | B58: BS: FY24–25 AR25 p131; FY23 AR24 p131; FY22 AR23 p122; FY21 AR22 p111 | C58: 37.6 | D58: 50.2 | E58: 53.8 | F58: 62.4 | G58: 69.4
A59: Assets held for sale | B59: BS: FY24–25 AR25 p131; FY23 AR24 p131; FY22 AR23 p122; FY21 AR22 p111 | C59: 1.6 | D59: 0 | E59: 0 | F59: 0 | G59: 0
A60: Current tax assets | B60: BS: FY24–25 AR25 p131; FY23 AR24 p131; FY22 AR23 p122; FY21 AR22 p111 | C60: 0.4 | D60: 0.6 | E60: 0 | F60: 0 | G60: 0
A61: Cash and cash equivalents | B61: BS: FY24–25 AR25 p131; FY23 AR24 p131; FY22 AR23 p122; FY21 AR22 p111 | C61: 198.6 | D61: 191.6 | E61: 195.3 | F61: 125.3 | G61: 70.8
A62: Current assets | B62: Formula | C62: =SUM(C57:C61) -> 266.1 | D62: =SUM(D57:D61) -> 283 | E62: =SUM(E57:E61) -> 297.9 | F62: =SUM(F57:F61) -> 242.9 | G62: =SUM(G57:G61) -> 195.9
A63: Total assets | B63: Formula | C63: =C56+C62 -> 888.4 | D63: =D56+D62 -> 974.4 | E63: =E56+E62 -> 1129.7 | F63: =F56+F62 -> 1319.7 | G63: =G56+G62 -> 1484
A64: Trade and other payables | B64: BS: FY24–25 AR25 p131; FY23 AR24 p131; FY22 AR23 p122; FY21 AR22 p111 | C64: -153.4 | D64: -191.7 | E64: -211.1 | F64: -243.9 | G64: -272.8
A65: Current tax liabilities | B65: BS: FY24–25 AR25 p131; FY23 AR24 p131; FY22 AR23 p122; FY21 AR22 p111 | C65: 0 | D65: 0 | E65: -4.9 | F65: -9.1 | G65: -2.1
A66: Lease liabilities (current) | B66: BS: FY24–25 AR25 p131; FY23 AR24 p131; FY22 AR23 p122; FY21 AR22 p111 | C66: -49.3 | D66: -48.8 | E66: -52.5 | F66: -53.8 | G66: -62.5
A67: Provisions (current) | B67: BS: FY24–25 AR25 p131; FY23 AR24 p131; FY22 AR23 p122; FY21 AR22 p111 | C67: -4.2 | D67: -3.6 | E67: -4 | F67: -3.4 | G67: -10.3
A68: Current liabilities | B68: Formula | C68: =SUM(C64:C67) -> -206.9 | D68: =SUM(D64:D67) -> -244.1 | E68: =SUM(E64:E67) -> -272.5 | F68: =SUM(F64:F67) -> -310.2 | G68: =SUM(G64:G67) -> -347.7
A69: Borrowings | B69: BS: FY24–25 AR25 p131; FY23 AR24 p131; FY22 AR23 p122; FY21 AR22 p111 | C69: 0 | D69: 0 | E69: 0 | F69: 0 | G69: -25
A70: Other payables (non-current) | B70: BS: FY24–25 AR25 p131; FY23 AR24 p131; FY22 AR23 p122; FY21 AR22 p111 | C70: -3.2 | D70: -2.8 | E70: -2.3 | F70: -1.8 | G70: -1.4
A71: Lease liabilities (non-current) | B71: BS: FY24–25 AR25 p131; FY23 AR24 p131; FY22 AR23 p122; FY21 AR22 p111 | C71: -233.9 | D71: -252.5 | E71: -267.1 | F71: -361.3 | G71: -387.3
A72: Deferred tax liability | B72: BS: FY24–25 AR25 p131; FY23 AR24 p131; FY22 AR23 p122; FY21 AR22 p111 | C72: -10 | D72: -26.3 | E72: -54.7 | F72: -72.6 | G72: -93.7
A73: Long-term provisions | B73: BS: FY24–25 AR25 p131; FY23 AR24 p131; FY22 AR23 p122; FY21 AR22 p111 | C73: -2.8 | D73: -2.7 | E73: -2.2 | F73: -2.9 | G73: -3.4
A74: Defined benefit pension liability | B74: BS: FY24–25 AR25 p131; FY23 AR24 p131; FY22 AR23 p122; FY21 AR22 p111 | C74: -2.4 | D74: 0 | E74: 0 | F74: -0.4 | G74: -0.3
A75: Non-current liabilities | B75: Formula | C75: =SUM(C69:C74) -> -252.3 | D75: =SUM(D69:D74) -> -284.3 | E75: =SUM(E69:E74) -> -326.3 | F75: =SUM(F69:F74) -> -439 | G75: =SUM(G69:G74) -> -511.1
A76: Total liabilities | B76: Formula | C76: =C68+C75 -> -459.2 | D76: =D68+D75 -> -528.4 | E76: =E68+E75 -> -598.8 | F76: =F68+F75 -> -749.2 | G76: =G68+G75 -> -858.8
A77: Net assets | B77: Formula | C77: =C63+C76 -> 429.2 | D77: =D63+D76 -> 446 | E77: =E63+E76 -> 530.9 | F77: =F63+F76 -> 570.5 | G77: =G63+G76 -> 625.2
A78: Issued capital | B78: BS: FY24–25 AR25 p131; FY23 AR24 p131; FY22 AR23 p122; FY21 AR22 p111 | C78: 2 | D78: 2 | E78: 2 | F78: 2 | G78: 2
A79: Share premium | B79: BS: FY24–25 AR25 p131; FY23 AR24 p131; FY22 AR23 p122; FY21 AR22 p111 | C79: 20 | D79: 23.1 | E79: 25.1 | F79: 25.1 | G79: 25.1
A80: Capital redemption reserve | B80: BS: FY24–25 AR25 p131; FY23 AR24 p131; FY22 AR23 p122; FY21 AR22 p111 | C80: 0.4 | D80: 0.4 | E80: 0.4 | F80: 0.4 | G80: 0.4
A81: Retained earnings | B81: BS: FY24–25 AR25 p131; FY23 AR24 p131; FY22 AR23 p122; FY21 AR22 p111 | C81: 406.8 | D81: 420.5 | E81: 503.4 | F81: 543 | G81: 597.7
A82: Total equity | B82: Formula | C82: =SUM(C78:C81) -> 429.2 | D82: =SUM(D78:D81) -> 446 | E82: =SUM(E78:E81) -> 530.9 | F82: =SUM(F78:F81) -> 570.5 | G82: =SUM(G78:G81) -> 625.2
A83: Reported total assets | B83: BS: FY24–25 AR25 p131; FY23 AR24 p131; FY22 AR23 p122; FY21 AR22 p111 | C83: 888.4 | D83: 974.4 | E83: 1129.7 | F83: 1319.7 | G83: 1484
A84: Reported net assets | B84: BS: FY24–25 AR25 p131; FY23 AR24 p131; FY22 AR23 p122; FY21 AR22 p111 | C84: 429.2 | D84: 446 | E84: 530.9 | F84: 570.5 | G84: 625.2
A86: Memo: net debt
A87: Net cash / (debt) excluding leases | B87: Formula | C87: =C61+C69 -> 198.6 | D87: =D61+D69 -> 191.6 | E87: =E61+E69 -> 195.3 | F87: =F61+F69 -> 125.3 | G87: =G61+G69 -> 45.8
A88: Total lease liabilities | B88: Formula | C88: =C66+C71 -> -283.2 | D88: =D66+D71 -> -301.3 | E88: =E66+E71 -> -319.6 | F88: =F66+F71 -> -415.1 | G88: =G66+G71 -> -449.8
A89: Net cash / (debt) including leases | B89: Formula | C89: =C87+C88 -> -84.6 | D89: =D87+D88 -> -109.7 | E89: =E87+E88 -> -124.3 | F89: =F87+F88 -> -289.8 | G89: =G87+G88 -> -404
A91: CASH FLOW STATEMENT (interest received shown in operating activities, as in FY25)
A92: Cash generated from operations | B92: CF: FY24–25 AR25 p134; FY23 AR24 p134; FY22 AR23 p125; FY21 AR22 p114 | C92: 312.1 | D92: 272.3 | E92: 333 | F92: 352.6 | G92: 383.7
A93: Income tax paid | B93: CF: FY24–25 AR25 p134; FY23 AR24 p134; FY22 AR23 p125; FY21 AR22 p114 | C93: -19.2 | D93: -13.3 | E93: -11.9 | F93: -27.7 | G93: -31.5
A94: Interest received | B94: CF: FY24–25 AR25 p134; FY23 AR24 p134; FY22 AR23 p125; FY21 AR22 p114 | C94: 0 | D94: 1.4 | E94: 6.1 | F94: 7.7 | G94: 2.1
A95: Interest paid on lease liabilities | B95: CF: FY24–25 AR25 p134; FY23 AR24 p134; FY22 AR23 p125; FY21 AR22 p114 | C95: -6.3 | D95: -6.8 | E95: -9.6 | F95: -13 | G95: -16.7
A96: Interest paid on borrowings and other charges | B96: CF: FY24–25 AR25 p134; FY23 AR24 p134; FY22 AR23 p125; FY21 AR22 p114 | C96: -1.1 | D96: -0.7 | E96: -0.7 | F96: -1 | G96: -0.6
A97: Net cash from operating activities | B97: Formula | C97: =SUM(C92:C96) -> 285.5 | D97: =SUM(D92:D96) -> 252.9 | E97: =SUM(E92:E96) -> 316.9 | F97: =SUM(F92:F96) -> 318.6 | G97: =SUM(G92:G96) -> 337
A98: Purchase of property, plant and equipment | B98: CF: FY24–25 AR25 p134; FY23 AR24 p134; FY22 AR23 p125; FY21 AR22 p114 | C98: -50.5 | D98: -100 | E98: -189.5 | F98: -230 | G98: -263.3
A99: Purchase of intangible assets | B99: CF: FY24–25 AR25 p134; FY23 AR24 p134; FY22 AR23 p125; FY21 AR22 p114 | C99: -3.8 | D99: -3.3 | E99: -8.6 | F99: -10.9 | G99: -22.1
A100: Proceeds from sale of PPE | B100: CF: FY24–25 AR25 p134; FY23 AR24 p134; FY22 AR23 p125; FY21 AR22 p114 | C100: 0.3 | D100: 0.9 | E100: 0.8 | F100: 16.1 | G100: 0.9
A101: Proceeds from sale of assets held for sale | B101: CF: FY24–25 AR25 p134; FY23 AR24 p134; FY22 AR23 p125; FY21 AR22 p114 | C101: 0 | D101: 1.6 | E101: 0 | F101: 0 | G101: 0
A102: Net cash from investing activities | B102: Formula | C102: =SUM(C98:C101) -> -54 | D102: =SUM(D98:D101) -> -100.8 | E102: =SUM(E98:E101) -> -197.3 | F102: =SUM(F98:F101) -> -224.8 | G102: =SUM(G98:G101) -> -284.5
A103: Proceeds from borrowing | B103: CF: FY24–25 AR25 p134; FY23 AR24 p134; FY22 AR23 p125; FY21 AR22 p114 | C103: 0 | D103: 0 | E103: 0 | F103: 0 | G103: 40
A104: Repayment of borrowing | B104: CF: FY24–25 AR25 p134; FY23 AR24 p134; FY22 AR23 p125; FY21 AR22 p114 | C104: 0 | D104: 0 | E104: 0 | F104: 0 | G104: -15
A105: Proceeds from issue of share capital | B105: CF: FY24–25 AR25 p134; FY23 AR24 p134; FY22 AR23 p125; FY21 AR22 p114 | C105: 4.3 | D105: 3.1 | E105: 2 | F105: 0 | G105: 0
A106: Sale of own shares | B106: CF: FY24–25 AR25 p134; FY23 AR24 p134; FY22 AR23 p125; FY21 AR22 p114 | C106: 0.3 | D106: 0 | E106: 1.6 | F106: 4.7 | G106: 1.6
...

Sheet Revenue
A1: Revenue build – company-managed shops and B2B (FY26–FY28)
A2: Session C: fill the yellow cells with formulas. FY25 (green) is the starting point. The Forecast tab reads company-managed and B2B revenue from rows 17 and 18.
A4: Line | B4: How to calculate | C4: FY25 | D4: FY26 | E4: FY27 | F4: FY28
A5: Company-managed shop roll-forward
A6: Company-managed shops at start of year | B6: Calculate: last year's closing shops | D6: =C8 -> 2137 | E6: =D8 -> 2203.15 | F6: =E8 -> 2272.45
A7: Company-managed net openings | B7: Calculate: net openings × company-managed share (Drivers) | C7: =Historical!G42-Historical!F42 -> 80 | D7: =Drivers!C7*Drivers!C6 -> 66.15 | E7: =Drivers!D6*Drivers!D7 -> 69.3 | F7: =Drivers!E6*Drivers!E7 -> 69.3
A8: Company-managed shops at end of year | B8: Calculate: start + net openings | C8: =Historical!G42 -> 2137 | D8: =D6+D7 -> 2203.15 | E8: =E6+E7 -> 2272.45 | F8: =F6+F7 -> 2341.75
A9: Sales per shop
A10: Like-for-like growth | B10: Calculate: link to Drivers | C10: =Historical!G47 -> 0.024 | D10: =Drivers!C8 -> 0.026 | E10: =Drivers!D8 -> 0.03 | F10: =Drivers!E8 -> 0.03
A11: Sales per mature shop (£m) | B11: Calculate: last year × (1 + LFL) | C11: =Historical!G49 -> 0.90472103 | D11: =C11*(1+D10) -> 0.92824378 | E11: =D11*(1+E10) -> 0.95609109 | F11: =E11*(1+F10) -> 0.98477382
A12: New-shop sales vs mature shop | B12: Calculate: link to Drivers | D12: =Drivers!C9 -> 0.85 | E12: =Drivers!D9 -> 0.85 | F12: =Drivers!E9 -> 0.85
A13: Company-managed revenue
A14: Existing estate | B14: Calculate: last year's company-managed revenue × (1 + LFL) | D14: =C17*(1+D10) -> 1946.5272 | E14: =D17*(1+E10) -> 2064.3094 | F14: =E17*(1+F10) -> 2182.9284
A15: Full-year effect of last year's openings | B15: Calculate: last year's net openings × 50% × sales per shop × new-shop % | D15: =C7*0.5*D11*D12 -> 31.560288 | E15: =D7*0.5*E11*E12 -> 26.879306 | F15: =E7*0.5*F11*F12 -> 29.004051
A16: This year's openings (half a year) | B16: Calculate: this year's net openings × 50% × sales per shop × new-shop % | D16: =D7*0.5*D11*D12 -> 26.096413 | E16: =E7*0.5*E11*E12 -> 28.159273 | F16: =F7*0.5*F11*F12 -> 29.004051
A17: Company-managed revenue | B17: Calculate: existing + full-year effect + this year's openings | C17: =Historical!G36 -> 1897.2 | D17: =D14+D15+D16 -> 2004.1839 | E17: =E14+E15+E16 -> 2119.348 | F17: =F14+F15+F16 -> 2240.9365
A18: B2B revenue | B18: Calculate: last year × (1 + B2B growth from Drivers) | C18: =Historical!G37 -> 254 | D18: =C18*(1+Drivers!C10) -> 279.4 | E18: =D18*(1+Drivers!D10) -> 301.752 | F18: =E18*(1+Drivers!E10) -> 325.89216
A19: Total revenue | B19: Calculate: company-managed + B2B | C19: =Historical!G7 -> 2151.2 | D19: =D17+D18 -> 2283.5839 | E19: =E17+E18 -> 2421.1 | F19: =F17+F18 -> 2566.8287
A20: Revenue growth | B20: Calculate: this year ÷ last year − 1 | D20: =(D19/C19)-1 -> 0.06153956 | E20: =(E19/D19)-1 -> 0.060219419 | F20: =(F19/E19)-1 -> 0.060191112
A21: Checks and sense checks
A22: Check: shops at end vs Forecast tab (should be 0) | B22: Filled for you | D22: =IF(D8="","",D8-Forecast!H42) -> 0 | E22: =IF(E8="","",E8-Forecast!I42) -> 0 | F22: =IF(F8="","",F8-Forecast!J42) -> 0
A24: Sense checks for FY26
A25: H1 2026 sales growth (26 weeks) | B25: H1 2026 presentation, slide 6 | C25: 0.072
A26: Edison FY26 revenue estimate, May 2026 (£m) | B26: Third-party estimate: use to sense-check, not as an input | C26: 2305.8
A27: Your FY26 revenue vs Edison | D27: =IF(D19="","",D19/C26-1) -> -0.0096348764

Sheet Forecast
A1: Greggs plc – forecast, FY26–FY28 (to build in Phase 2)
A2: FY21–FY25 link to Historical (green). FY26–FY28 are formulas driven by the Drivers and Revenue tabs; supporting schedules are at the bottom of this tab.
A3: FY26 is a 52-week year to 26 Dec 2026. Revenue comes from the Revenue tab (Session C).
A4: £m | B4: How to forecast (Phase 2) | C4: FY21 | D4: FY22 | E4: FY23 | F4: FY24 | G4: FY25 | H4: FY26 | I4: FY27 | J4: FY28
A6: INCOME STATEMENT (statutory, including exceptional items)
A7: Revenue | B7: Sum of company-managed and B2B | C7: =Historical!C7 -> 1229.7 | D7: =Historical!D7 -> 1512.8 | E7: =Historical!E7 -> 1809.6 | F7: =Historical!F7 -> 2014.4 | G7: =Historical!G7 -> 2151.2 | H7: =H36+H37 -> 2283.5839 | I7: =I36+I37 -> 2421.1 | J7: =J36+J37 -> 2566.8287
A8: Cost of sales | C8: =Historical!C8 -> -447.7 | D8: =Historical!D8 -> -574.5 | E8: =Historical!E8 -> -710.5 | F8: =Historical!F8 -> -770.8 | G8: =Historical!G8 -> -829.1 | H8: =-H7*(1-Drivers!$C$21) -> -879.1798 | I8: =-I7*(1-Drivers!$D$21) -> -932.1235 | J8: =-J7*(1-Drivers!$E$21) -> -988.22905
A9: Gross profit | C9: =Historical!C9 -> 782 | D9: =Historical!D9 -> 938.3 | E9: =Historical!E9 -> 1099.1 | F9: =Historical!F9 -> 1243.6 | G9: =Historical!G9 -> 1322.1 | H9: =H7+H8 -> 1404.4041 | I9: =I7+I8 -> 1488.9765 | J9: =J7+J8 -> 1578.5997
A10: Distribution and selling costs | C10: =Historical!C10 -> -567.6 | D10: =Historical!D10 -> -713.2 | E10: =Historical!E10 -> -844.2 | F10: =Historical!F10 -> -950.1 | G10: =Historical!G10 -> -1036.3 | H10: =Drivers!$C$11*H7-H7-H8+H153 -> -1096.1203 | I10: =Drivers!$D$11*I7-I7-I8+I153 -> -1157.2858 | J10: =Drivers!$E$11*J7-J7-J8+J153 -> -1219.2436
A11: Administrative expenses | C11: =Historical!C11 -> -61.2 | D11: =Historical!D11 -> -70.7 | E11: =Historical!E11 -> -82.9 | F11: =Historical!F11 -> -97.9 | G11: =Historical!G11 -> -102.1 | H11: =-H153+H21 -> -152.32844 | I11: =-I153+I21 -> -123.7917 | J11: =-J153+J21 -> -125.64095
A12: Other income (exceptional) | C12: =Historical!C12 -> 0 | D12: =Historical!D12 -> 0 | E12: =Historical!E12 -> 20.3 | F12: =Historical!F12 -> 13.8 | G12: =Historical!G12 -> 0 | H12: =0 -> 0 | I12: =0 -> 0 | J12: =0 -> 0
A13: Operating profit | C13: =Historical!C13 -> 153.2 | D13: =Historical!D13 -> 154.4 | E13: =Historical!E13 -> 192.3 | F13: =Historical!F13 -> 209.4 | G13: =Historical!G13 -> 183.7 | H13: =H9+H10+H11+H12 -> 155.95538 | I13: =I9+I10+I11+I12 -> 207.899 | J13: =J9+J10+J11+J12 -> 233.71507
A14: Finance income | C14: =Historical!C14 -> 0 | D14: =Historical!D14 -> 1.4 | E14: =Historical!E14 -> 6.1 | F14: =Historical!F14 -> 8.1 | G14: =Historical!G14 -> 1.8 | H14: =H152 -> 2.124 | I14: =I152 -> 2.6411242 | J14: =J152 -> 3.3144792
A15: Finance expense | C15: =Historical!C15 -> -7.6 | D15: =Historical!D15 -> -7.5 | E15: =Historical!E15 -> -10.1 | F15: =Historical!F15 -> -13.6 | G15: =Historical!G15 -> -18.1 | H15: =-H150-H151 -> -18.7922 | I15: =-I150-I151 -> -19.335212 | J15: =-J150-J151 -> -19.904082
A16: Profit before tax | C16: =Historical!C16 -> 145.6 | D16: =Historical!D16 -> 148.3 | E16: =Historical!E16 -> 188.3 | F16: =Historical!F16 -> 203.9 | G16: =Historical!G16 -> 167.4 | H16: =H13+H14+H15 -> 139.28718 | I16: =I13+I14+I15 -> 191.20491 | J16: =J13+J14+J15 -> 217.12547
A17: Income tax | B17: PBT x tax rate | C17: =Historical!C17 -> -28.1 | D17: =Historical!D17 -> -28 | E17: =Historical!E17 -> -45.8 | F17: =Historical!F17 -> -50.5 | G17: =Historical!G17 -> -45.2 | H17: =-Drivers!$C$18*H16 -> -36.214668 | I17: =-Drivers!$D$18*I16 -> -49.713277 | J17: =-Drivers!$E$18*J16 -> -56.452621
A18: Profit for the year | C18: =Historical!C18 -> 117.5 | D18: =Historical!D18 -> 120.3 | E18: =Historical!E18 -> 142.5 | F18: =Historical!F18 -> 153.4 | G18: =Historical!G18 -> 122.2 | H18: =H16+H17 -> 103.07252 | I18: =I16+I17 -> 141.49163 | J18: =J16+J17 -> 160.67285
A20: Exceptional items and underlying profit
A21: Exceptional items within operating profit | B21: Restructuring cost (c.£60m cash, FY26–28) on its own line | C21: =Historical!C21 -> 0 | D21: =Historical!D21 -> 0 | E21: =Historical!E21 -> 20.6 | F21: =Historical!F21 -> 14.1 | G21: =Historical!G21 -> -3.8 | H21: =-H154 -> -45 | I21: =-I154 -> -10 | J21: =-J154 -> -5
A22: Exceptional items within finance expense | C22: =Historical!C22 -> 0 | D22: =Historical!D22 -> 0 | E22: =Historical!E22 -> 0 | F22: =Historical!F22 -> 0 | G22: =Historical!G22 -> -0.7 | H22: =0 -> 0 | I22: =0 -> 0 | J22: =0 -> 0
A23: Tax on exceptional items | C23: =Historical!C23 -> 0 | D23: =Historical!D23 -> 0 | E23: =Historical!E23 -> -4.8 | F23: =Historical!F23 -> -1.7 | G23: =Historical!G23 -> 0.9 | H23: =-H21*Drivers!$C$18 -> 11.7 | I23: =-I21*Drivers!$D$18 -> 2.6 | J23: =-J21*Drivers!$E$18 -> 1.3
A24: Underlying operating profit | B24: Revenue x underlying operating margin | C24: =Historical!C24 -> 153.2 | D24: =Historical!D24 -> 154.4 | E24: =Historical!E24 -> 171.7 | F24: =Historical!F24 -> 195.3 | G24: =Historical!G24 -> 187.5 | H24: =H13-H21 -> 200.95538 | I24: =I13-I21 -> 217.899 | J24: =J13-J21 -> 238.71507
A25: Underlying profit before tax | C25: =Historical!C25 -> 145.6 | D25: =Historical!D25 -> 148.3 | E25: =Historical!E25 -> 167.7 | F25: =Historical!F25 -> 189.8 | G25: =Historical!G25 -> 171.9 | H25: =H16-H21-H22 -> 184.28718 | I25: =I16-I21-I22 -> 201.20491 | J25: =J16-J21-J22 -> 222.12547
A26: Underlying operating margin | C26: =Historical!C26 -> 0.12458323 | D26: =Historical!D26 -> 0.1020624 | E26: =Historical!E26 -> 0.094882847 | F26: =Historical!F26 -> 0.096951946 | G26: =Historical!G26 -> 0.087160655 | H26: =IF(H7=0,0,H24/H7) -> 0.088 | I26: =IF(I7=0,0,I24/I7) -> 0.09 | J26: =IF(J7=0,0,J24/J7) -> 0.093
A27: Effective tax rate (statutory) | C27: =Historical!C27 -> 0.19299451 | D27: =Historical!D27 -> 0.18880647 | E27: =Historical!E27 -> 0.24322889 | F27: =Historical!F27 -> 0.24767043 | G27: =Historical!G27 -> 0.27001195 | H27: =IF(H16=0,0,-H17/H16) -> 0.26 | I27: =IF(I16=0,0,-I17/I16) -> 0.26 | J27: =IF(J16=0,0,-J17/J16) -> 0.26
A29: Reported totals (typed from the reports, for the checks)
A30: Reported operating profit | C30: =Historical!C30 -> 153.2 | D30: =Historical!D30 -> 154.4 | E30: =Historical!E30 -> 192.3 | F30: =Historical!F30 -> 209.4 | G30: =Historical!G30 -> 183.7
A31: Reported profit before tax | C31: =Historical!C31 -> 145.6 | D31: =Historical!D31 -> 148.3 | E31: =Historical!E31 -> 188.3 | F31: =Historical!F31 -> 203.9 | G31: =Historical!G31 -> 167.4
A32: Reported profit for the year | C32: =Historical!C32 -> 117.5 | D32: =Historical!D32 -> 120.3 | E32: =Historical!E32 -> 142.5 | F32: =Historical!F32 -> 153.4 | G32: =Historical!G32 -> 122.2
A33: Reported underlying PBT | C33: =Historical!C33 -> 145.6 | D33: =Historical!D33 -> 148.3 | E33: =Historical!E33 -> 167.7 | F33: =Historical!F33 -> 189.8 | G33: =Historical!G33 -> 171.9
A35: REVENUE SPLIT AND SHOP KPIs
A36: Revenue: company-managed shops | B36: Shop roll-forward x sales per shop, grown by LFL | C36: =Historical!C36 -> 1098.2 | D36: =Historical!D36 -> 1352.3 | E36: =Historical!E36 -> 1610.9 | F36: =Historical!F36 -> 1781.7 | G36: =Historical!G36 -> 1897.2 | H36: =Revenue!D17 -> 2004.1839 | I36: =Revenue!E17 -> 2119.348 | J36: =Revenue!F17 -> 2240.9365
A37: Revenue: business to business (franchise, wholesale, grocery) | B37: Growth rate on franchise and wholesale | C37: =Historical!C37 -> 131.5 | D37: =Historical!D37 -> 160.5 | E37: =Historical!E37 -> 198.7 | F37: =Historical!F37 -> 232.7 | G37: =Historical!G37 -> 254 | H37: =Revenue!D18 -> 279.4 | I37: =Revenue!E18 -> 301.752 | J37: =Revenue!F18 -> 325.89216
A38: Check: split less revenue (should be 0) | C38: =Historical!C38 -> 0 | D38: =Historical!D38 -> 0 | E38: =Historical!E38 -> 0 | F38: =Historical!F38 -> 0 | G38: =Historical!G38 -> 0 | H38: =H36+H37-H7 -> 0 | I38: =I36+I37-I7 -> 0 | J38: =J36+J37-J7 -> 0
A39: Shops at start of year | C39: =Historical!C39 -> 2078 | D39: =Historical!D39 -> 2181 | E39: =Historical!E39 -> 2328 | F39: =Historical!F39 -> 2473 | G39: =Historical!G39 -> 2618 | H39: =G40 -> 2739 | I39: =H40 -> 2844 | J39: =I40 -> 2954
A40: Shops at year end (total) | B40: Opening shops + net openings | C40: =Historical!C40 -> 2181 | D40: =Historical!D40 -> 2328 | E40: =Historical!E40 -> 2473 | F40: =Historical!F40 -> 2618 | G40: =Historical!G40 -> 2739 | H40: =H39+Drivers!$C$6 -> 2844 | I40: =I39+Drivers!$D$6 -> 2954 | J40: =J39+Drivers!$E$6 -> 3064
A41: of which franchised | C41: =Historical!C41 -> 375 | D41: =Historical!D41 -> 441 | E41: =Historical!E41 -> 503 | F41: =Historical!F41 -> 561 | G41: =Historical!G41 -> 602 | H41: =G41+(1-Drivers!$C$7)*Drivers!$C$6 -> 640.85 | I41: =H41+(1-Drivers!$D$7)*Drivers!$D$6 -> 681.55 | J41: =I41+(1-Drivers!$E$7)*Drivers!$E$6 -> 722.25
A42: of which company-managed | C42: =Historical!C42 -> 1806 | D42: =Historical!D42 -> 1887 | E42: =Historical!E42 -> 1970 | F42: =Historical!F42 -> 2057 | G42: =Historical!G42 -> 2137 | H42: =IF(H41="","",H40-H41) -> 2203.15 | I42: =IF(I41="","",I40-I41) -> 2272.45 | J42: =IF(J41="","",J40-J41) -> 2341.75
A43: Gross openings | C43: =Historical!C43 -> 131 | D43: =Historical!D43 -> 186 | E43: =Historical!E43 -> 220 | F43: =Historical!F43 -> 226 | G43: =Historical!G43 -> 207
A44: Closures (incl. relocations) | C44: =Historical!C44 -> -28 | D44: =Historical!D44 -> -39 | E44: =Historical!E44 -> -75 | F44: =Historical!F44 -> -81 | G44: =Historical!G44 -> -86
A45: Net openings | C45: =Historical!C45 -> 103 | D45: =Historical!D45 -> 147 | E45: =Historical!E45 -> 145 | F45: =Historical!F45 -> 145 | G45: =Historical!G45 -> 121 | H45: =H40-H39 -> 105 | I45: =I40-I39 -> 110 | J45: =J40-J39 -> 110
A46: Check: openings + closures less net (should be 0) | C46: =Historical!C46 -> 0 | D46: =Historical!D46 -> 0 | E46: =Historical!E46 -> 0 | F46: =Historical!F46 -> 0 | G46: =Historical!G46 -> 0 | H46: =IF(H43="",0,H43+H44-H45) -> 0 | I46: =IF(I43="",0,I43+I44-I45) -> 0 | J46: =IF(J43="",0,J43+J44-J45) -> 0
A47: Company-managed like-for-like sales growth | C47: =Historical!C47 -> 0.524 | D47: =Historical!D47 -> 0.178 | E47: =Historical!E47 -> 0.137 | F47: =Historical!F47 -> 0.055 | G47: =Historical!G47 -> 0.024 | H47: =Drivers!$C$8 -> 0.026 | I47: =Drivers!$D$8 -> 0.03 | J47: =Drivers!$E$8 -> 0.03
A48: Franchise like-for-like system sales growth | C48: =Historical!C48 -> 0 | D48: =Historical!D48 -> 0 | E48: =Historical!E48 -> 0.149 | F48: =Historical!F48 -> 0.074 | G48: =Historical!G48 -> 0.043
A49: Company-managed revenue per average shop (£m) | C49: =Historical!C49 -> 0.60808416 | D49: =Historical!D49 -> 0.73235852 | E49: =Historical!E49 -> 0.83531242 | F49: =Historical!F49 -> 0.88487708 | G49: =Historical!G49 -> 0.90472103 | H49: =IF(H42="","",H36/AVERAGE(H42,IF(G42="",H42,G42))) -> 0.92355513 | I49: =IF(I42="","",I36/AVERAGE(I42,IF(H42="",I42,H42))) -> 0.94706765 | J49: =IF(J42="","",J36/AVERAGE(J42,IF(I42="",J42,I42))) -> 0.97132181
A51: BALANCE SHEET (group)
A52: Intangible assets | C52: =Historical!C52 -> 14.9 | D52: =Historical!D52 -> 13.5 | E52: =Historical!E52 -> 18.3 | F52: =Historical!F52 -> 24.9 | G52: =Historical!G52 -> 43 | H52: =G52+H142-H144 -> 49.66 | I52: =H52+I142-I144 -> 53.9212 | J52: =I52+J142-J144 -> 57.015384
A53: Property, plant and equipment | B53: Opening + capex - depreciation (schedule) | C53: =Historical!C53 -> 343.8 | D53: =Historical!D53 -> 390 | E53: =Historical!E53 -> 510.3 | F53: =Historical!F53 -> 664.7 | G53: =Historical!G53 -> 832.1 | H53: =G53+H143-H145 -> 885.3665 | I53: =H53+I143-I145 -> 917.64202 | J53: =I53+J143-J145 -> 940.96035
A54: Right-of-use assets | B54: Grows with shop numbers (schedule) | C54: =Historical!C54 -> 263.6 | D54: =Historical!D54 -> 281.6 | E54: =Historical!E54 -> 296.6 | F54: =Historical!F54 -> 387.2 | G54: =Historical!G54 -> 413 | H54: =G54*H42/G42 -> 425.78425 | I54: =H54*I42/H42 -> 439.17728 | J54: =I54*J42/I42 -> 452.57031
A55: Defined benefit pension asset | C55: =Historical!C55 -> 0 | D55: =Historical!D55 -> 6.3 | E55: =Historical!E55 -> 6.6 | F55: =Historical!F55 -> 0 | G55: =Historical!G55 -> 0 | H55: =0 -> 0 | I55: =0 -> 0 | J55: =0 -> 0
A56: Non-current assets | C56: =Historical!C56 -> 622.3 | D56: =Historical!D56 -> 691.4 | E56: =Historical!E56 -> 831.8 | F56: =Historical!F56 -> 1076.8 | G56: =Historical!G56 -> 1288.1 | H56: =SUM(H52:H55) -> 1360.8108 | I56: =SUM(I52:I55) -> 1410.7405 | J56: =SUM(J52:J55) -> 1450.546
A57: Inventories | B57: Days of cost of sales | C57: =Historical!C57 -> 27.9 | D57: =Historical!D57 -> 40.6 | E57: =Historical!E57 -> 48.8 | F57: =Historical!F57 -> 55.2 | G57: =Historical!G57 -> 55.7 | H57: =-H8*Drivers!$C$23/365 -> 60.217795 | I57: =-I8*Drivers!$D$23/365 -> 63.844075 | J57: =-J8*Drivers!$E$23/365 -> 67.686921
A58: Trade and other receivables | B58: Days of revenue | C58: =Historical!C58 -> 37.6 | D58: =Historical!D58 -> 50.2 | E58: =Historical!E58 -> 53.8 | F58: =Historical!F58 -> 62.4 | G58: =Historical!G58 -> 69.4 | H58: =H7*Drivers!$C$24/365 -> 71.948534 | I58: =I7*Drivers!$D$24/365 -> 76.281233 | J58: =J7*Drivers!$E$24/365 -> 80.872685
A59: Assets held for sale | C59: =Historical!C59 -> 1.6 | D59: =Historical!D59 -> 0 | E59: =Historical!E59 -> 0 | F59: =Historical!F59 -> 0 | G59: =Historical!G59 -> 0 | H59: =0 -> 0 | I59: =0 -> 0 | J59: =0 -> 0
A60: Current tax assets | C60: =Historical!C60 -> 0.4 | D60: =Historical!D60 -> 0.6 | E60: =Historical!E60 -> 0 | F60: =Historical!F60 -> 0 | G60: =Historical!G60 -> 0 | H60: =0 -> 0 | I60: =0 -> 0 | J60: =0 -> 0
A61: Cash and cash equivalents | B61: From cash flow, never typed | C61: =Historical!C61 -> 198.6 | D61: =Historical!D61 -> 191.6 | E61: =Historical!E61 -> 195.3 | F61: =Historical!F61 -> 125.3 | G61: =Historical!G61 -> 70.8 | H61: =H113 -> 88.037473 | I61: =I113 -> 110.48264 | J61: =J113 -> 175.22241
A62: Current assets | C62: =Historical!C62 -> 266.1 | D62: =Historical!D62 -> 283 | E62: =Historical!E62 -> 297.9 | F62: =Historical!F62 -> 242.9 | G62: =Historical!G62 -> 195.9 | H62: =SUM(H57:H61) -> 220.2038 | I62: =SUM(I57:I61) -> 250.60795 | J62: =SUM(J57:J61) -> 323.78202
A63: Total assets | C63: =Historical!C63 -> 888.4 | D63: =Historical!D63 -> 974.4 | E63: =Historical!E63 -> 1129.7 | F63: =Historical!F63 -> 1319.7 | G63: =Historical!G63 -> 1484 | H63: =H56+H62 -> 1581.0146 | I63: =I56+I62 -> 1661.3485 | J63: =J56+J62 -> 1774.3281
A64: Trade and other payables | B64: Days of cost of sales | C64: =Historical!C64 -> -153.4 | D64: =Historical!D64 -> -191.7 | E64: =Historical!E64 -> -211.1 | F64: =Historical!F64 -> -243.9 | G64: =Historical!G64 -> -272.8 | H64: =-H7*Drivers!$C$25/365 -> -281.53774 | I64: =-I7*Drivers!$D$25/365 -> -298.49178 | J64: =-J7*Drivers!$E$25/365 -> -316.45833
A65: Current tax liabilities | C65: =Historical!C65 -> 0 | D65: =Historical!D65 -> 0 | E65: =Historical!E65 -> -4.9 | F65: =Historical!F65 -> -9.1 | G65: =Historical!G65 -> -2.1 | H65: =G65 -> -2.1 | I65: =H65 -> -2.1 | J65: =I65 -> -2.1
A66: Lease liabilities (current) | B66: Lease schedule | C66: =Historical!C66 -> -49.3 | D66: =Historical!D66 -> -48.8 | E66: =Historical!E66 -> -52.5 | F66: =Historical!F66 -> -53.8 | G66: =Historical!G66 -> -62.5 | H66: =-H146*Drivers!$C$35 -> -64.45755 | I66: =-I146*Drivers!$D$35 -> -66.48506 | J66: =-J146*Drivers!$E$35 -> -68.51257
A67: Provisions (current) | C67: =Historical!C67 -> -4.2 | D67: =Historical!D67 -> -3.6 | E67: =Historical!E67 -> -4 | F67: =Historical!F67 -> -3.4 | G67: =Historical!G67 -> -10.3 | H67: =G67-(H154-H155) -> -45.3 | I67: =H67-(I154-I155) -> -20.3 | J67: =I67-(J154-J155) -> -10.3
A68: Current liabilities | C68: =Historical!C68 -> -206.9 | D68: =Historical!D68 -> -244.1 | E68: =Historical!E68 -> -272.5 | F68: =Historical!F68 -> -310.2 | G68: =Historical!G68 -> -347.7 | H68: =SUM(H64:H67) -> -393.39529 | I68: =SUM(I64:I67) -> -387.37684 | J68: =SUM(J64:J67) -> -397.3709
A69: Borrowings | C69: =Historical!C69 -> 0 | D69: =Historical!D69 -> 0 | E69: =Historical!E69 -> 0 | F69: =Historical!F69 -> 0 | G69: =Historical!G69 -> -25 | H69: =G69 -> -25 | I69: =H69 -> -25 | J69: =I69 -> -25
A70: Other payables (non-current) | C70: =Historical!C70 -> -3.2 | D70: =Historical!D70 -> -2.8 | E70: =Historical!E70 -> -2.3 | F70: =Historical!F70 -> -1.8 | G70: =Historical!G70 -> -1.4 | H70: =G70 -> -1.4 | I70: =H70 -> -1.4 | J70: =I70 -> -1.4
A71: Lease liabilities (non-current) | B71: Lease schedule | C71: =Historical!C71 -> -233.9 | D71: =Historical!D71 -> -252.5 | E71: =Historical!E71 -> -267.1 | F71: =Historical!F71 -> -361.3 | G71: =Historical!G71 -> -387.3 | H71: =-H146*(1-Drivers!$C$35) -> -399.26583 | I71: =-I146*(1-Drivers!$D$35) -> -411.82472 | J71: =-J146*(1-Drivers!$E$35) -> -424.38362
A72: Deferred tax liability | C72: =Historical!C72 -> -10 | D72: =Historical!D72 -> -26.3 | E72: =Historical!E72 -> -54.7 | F72: =Historical!F72 -> -72.6 | G72: =Historical!G72 -> -93.7 | H72: =G72-H156 -> -100.29192 | I72: =H72-I156 -> -104.31095 | J72: =I72-J156 -> -107.21633
A73: Long-term provisions | C73: =Historical!C73 -> -2.8 | D73: =Historical!D73 -> -2.7 | E73: =Historical!E73 -> -2.2 | F73: =Historical!F73 -> -2.9 | G73: =Historical!G73 -> -3.4 | H73: =G73 -> -3.4 | I73: =H73 -> -3.4 | J73: =I73 -> -3.4
A74: Defined benefit pension liability | C74: =Historical!C74 -> -2.4 | D74: =Historical!D74 -> 0 | E74: =Historical!E74 -> 0 | F74: =Historical!F74 -> -0.4 | G74: =Historical!G74 -> -0.3 | H74: =G74 -> -0.3 | I74: =H74 -> -0.3 | J74: =I74 -> -0.3
A75: Non-current liabilities | C75: =Historical!C75 -> -252.3 | D75: =Historical!D75 -> -284.3 | E75: =Historical!E75 -> -326.3 | F75: =Historical!F75 -> -439 | G75: =Historical!G75 -> -511.1 | H75: =SUM(H69:H74) -> -529.65775 | I75: =SUM(I69:I74) -> -546.23568 | J75: =SUM(J69:J74) -> -561.69995
A76: Total liabilities | C76: =Historical!C76 -> -459.2 | D76: =Historical!D76 -> -528.4 | E76: =Historical!E76 -> -598.8 | F76: =Historical!F76 -> -749.2 | G76: =Historical!G76 -> -858.8 | H76: =H68+H75 -> -923.05304 | I76: =I68+I75 -> -933.61252 | J76: =J68+J75 -> -959.07085
A77: Net assets | C77: =Historical!C77 -> 429.2 | D77: =Historical!D77 -> 446 | E77: =Historical!E77 -> 530.9 | F77: =Historical!F77 -> 570.5 | G77: =Historical!G77 -> 625.2 | H77: =H63+H76 -> 657.96152 | I77: =I63+I76 -> 727.73593 | J77: =J63+J76 -> 815.25721
A78: Issued capital | C78: =Historical!C78 -> 2 | D78: =Historical!D78 -> 2 | E78: =Historical!E78 -> 2 | F78: =Historical!F78 -> 2 | G78: =Historical!G78 -> 2 | H78: =G78 -> 2 | I78: =H78 -> 2 | J78: =I78 -> 2
A79: Share premium | C79: =Historical!C79 -> 20 | D79: =Historical!D79 -> 23.1 | E79: =Historical!E79 -> 25.1 | F79: =Historical!F79 -> 25.1 | G79: =Historical!G79 -> 25.1 | H79: =G79 -> 25.1 | I79: =H79 -> 25.1 | J79: =I79 -> 25.1
A80: Capital redemption reserve | C80: =Historical!C80 -> 0.4 | D80: =Historical!D80 -> 0.4 | E80: =Historical!E80 -> 0.4 | F80: =Historical!F80 -> 0.4 | G80: =Historical!G80 -> 0.4 | H80: =G80 -> 0.4 | I80: =H80 -> 0.4 | J80: =I80 -> 0.4
A81: Retained earnings | B81: Opening + profit - dividends - buybacks | C81: =Historical!C81 -> 406.8 | D81: =Historical!D81 -> 420.5 | E81: =Historical!E81 -> 503.4 | F81: =Historical!F81 -> 543 | G81: =Historical!G81 -> 597.7 | H81: =G81+H18+H108 -> 630.46152 | I81: =H81+I18+I108 -> 700.23593 | J81: =I81+J18+J108 -> 787.75721
A82: Total equity | C82: =Historical!C82 -> 429.2 | D82: =Historical!D82 -> 446 | E82: =Historical!E82 -> 530.9 | F82: =Historical!F82 -> 570.5 | G82: =Historical!G82 -> 625.2 | H82: =SUM(H78:H81) -> 657.96152 | I82: =SUM(I78:I81) -> 727.73593 | J82: =SUM(J78:J81) -> 815.25721
A83: Reported total assets | C83: =Historical!C83 -> 888.4 | D83: =Historical!D83 -> 974.4 | E83: =Historical!E83 -> 1129.7 | F83: =Historical!F83 -> 1319.7 | G83: =Historical!G83 -> 1484
A84: Reported net assets | C84: =Historical!C84 -> 429.2 | D84: =Historical!D84 -> 446 | E84: =Historical!E84 -> 530.9 | F84: =Historical!F84 -> 570.5 | G84: =Historical!G84 -> 625.2
A86: Memo: net debt
A87: Net cash / (debt) excluding leases | C87: =Historical!C87 -> 198.6 | D87: =Historical!D87 -> 191.6 | E87: =Historical!E87 -> 195.3 | F87: =Historical!F87 -> 125.3 | G87: =Historical!G87 -> 45.8 | H87: =H61+H69 -> 63.037473 | I87: =I61+I69 -> 85.482639 | J87: =J61+J69 -> 150.22241
A88: Total lease liabilities | C88: =Historical!C88 -> -283.2 | D88: =Historical!D88 -> -301.3 | E88: =Historical!E88 -> -319.6 | F88: =Historical!F88 -> -415.1 | G88: =Historical!G88 -> -449.8 | H88: =H66+H71 -> -463.72338 | I88: =I66+I71 -> -478.30978 | J88: =J66+J71 -> -492.89619
A89: Net cash / (debt) including leases | C89: =Historical!C89 -> -84.6 | D89: =Historical!D89 -> -109.7 | E89: =Historical!E89 -> -124.3 | F89: =Historical!F89 -> -289.8 | G89: =Historical!G89 -> -404 | H89: =H87+H88 -> -400.68591 | I89: =I87+I88 -> -392.82715 | J89: =J87+J88 -> -342.67377
A91: CASH FLOW STATEMENT (interest received shown in operating activities, as in FY25)
A92: Cash generated from operations | C92: =Historical!C92 -> 312.1 | D92: =Historical!D92 -> 272.3 | E92: =Historical!E92 -> 333 | F92: =Historical!F92 -> 352.6 | G92: =Historical!G92 -> 383.7 | H92: =H13+H145+H144+H147-(H57-G57)-(H58-G58)-(H64-G64)-(H67-G67) -> 382.9103 | I92: =I13+I145+I144+I147-(I57-H57)-(I58-H58)-(I64-H64)-(I67-H67) -> 392.74066 | J92: =J13+J145+J144+J147-(J57-I57)-(J58-I58)-(J64-I64)-(J67-I67) -> 441.49495
A93: Income tax paid | C93: =Historical!C93 -> -19.2 | D93: =Historical!D93 -> -13.3 | E93: =Historical!E93 -> -11.9 | F93: =Historical!F93 -> -27.7 | G93: =Historical!G93 -> -31.5 | H93: =H17-(H72-G72) -> -29.622753 | I93: =I17-(I72-H72) -> -45.694238 | J93: =J17-(J72-I72) -> -53.547245
A94: Interest received | C94: =Historical!C94 -> 0 | D94: =Historical!D94 -> 1.4 | E94: =Historical!E94 -> 6.1 | F94: =Historical!F94 -> 7.7 | G94: =Historical!G94 -> 2.1 | H94: =H14 -> 2.124 | I94: =I14 -> 2.6411242 | J94: =J14 -> 3.3144792
A95: Interest paid on lease liabilities | C95: =Historical!C95 -> -6.3 | D95: =Historical!D95 -> -6.8 | E95: =Historical!E95 -> -9.6 | F95: =Historical!F95 -> -13 | G95: =Historical!G95 -> -16.7 | H95: =-H150 -> -17.5422 | I95: =-I150 -> -18.085212 | J95: =-J150 -> -18.654082
A96: Interest paid on borrowings and other charges | C96: =Historical!C96 -> -1.1 | D96: =Historical!D96 -> -0.7 | E96: =Historical!E96 -> -0.7 | F96: =Historical!F96 -> -1 | G96: =Historical!G96 -> -0.6 | H96: =-H151 -> -1.25 | I96: =-I151 -> -1.25 | J96: =-J151 -> -1.25
A97: Net cash from operating activities | B97: Built from IS and balance sheet movements | C97: =Historical!C97 -> 285.5 | D97: =Historical!D97 -> 252.9 | E97: =Historical!E97 -> 316.9 | F97: =Historical!F97 -> 318.6 | G97: =Historical!G97 -> 337 | H97: =SUM(H92:H96) -> 336.61934 | I97: =SUM(I92:I96) -> 330.35233 | J97: =SUM(J92:J96) -> 371.3581
A98: Purchase of property, plant and equipment | C98: =Historical!C98 -> -50.5 | D98: =Historical!D98 -> -100 | E98: =Historical!E98 -> -189.5 | F98: =Historical!F98 -> -230 | G98: =Historical!G98 -> -263.3 | H98: =-H143 -> -165.6 | I98: =-I143 -> -151.8 | J98: =-J143 -> -147.2
A99: Purchase of intangible assets | C99: =Historical!C99 -> -3.8 | D99: =Historical!D99 -> -3.3 | E99: =Historical!E99 -> -8.6 | F99: =Historical!F99 -> -10.9 | G99: =Historical!G99 -> -22.1 | H99: =-H142 -> -14.4 | I99: =-I142 -> -13.2 | J99: =-J142 -> -12.8
A100: Proceeds from sale of PPE | C100: =Historical!C100 -> 0.3 | D100: =Historical!D100 -> 0.9 | E100: =Historical!E100 -> 0.8 | F100: =Historical!F100 -> 16.1 | G100: =Historical!G100 -> 0.9 | H100: =0 -> 0 | I100: =0 -> 0 | J100: =0 -> 0
A101: Proceeds from sale of assets held for sale | C101: =Historical!C101 -> 0 | D101: =Historical!D101 -> 1.6 | E101: =Historical!E101 -> 0 | F101: =Historical!F101 -> 0 | G101: =Historical!G101 -> 0 | H101: =0 -> 0 | I101: =0 -> 0 | J101: =0 -> 0
A102: Net cash from investing activities | C102: =Historical!C102 -> -54 | D102: =Historical!D102 -> -100.8 | E102: =Historical!E102 -> -197.3 | F102: =Historical!F102 -> -224.8 | G102: =Historical!G102 -> -284.5 | H102: =SUM(H98:H101) -> -180 | I102: =SUM(I98:I101) -> -165 | J102: =SUM(J98:J101) -> -160
A103: Proceeds from borrowing | C103: =Historical!C103 -> 0 | D103: =Historical!D103 -> 0 | E103: =Historical!E103 -> 0 | F103: =Historical!F103 -> 0 | G103: =Historical!G103 -> 40 | H103: =0 -> 0 | I103: =0 -> 0 | J103: =0 -> 0
A104: Repayment of borrowing | C104: =Historical!C104 -> 0 | D104: =Historical!D104 -> 0 | E104: =Historical!E104 -> 0 | F104: =Historical!F104 -> 0 | G104: =Historical!G104 -> -15 | H104: =0 -> 0 | I104: =0 -> 0 | J104: =0 -> 0
A105: Proceeds from issue of share capital | C105: =Historical!C105 -> 4.3 | D105: =Historical!D105 -> 3.1 | E105: =Historical!E105 -> 2 | F105: =Historical!F105 -> 0 | G105: =Historical!G105 -> 0 | H105: =0 -> 0 | I105: =0 -> 0 | J105: =0 -> 0
A106: Sale of own shares | C106: =Historical!C106 -> 0.3 | D106: =Historical!D106 -> 0 | E106: =Historical!E106 -> 1.6 | F106: =Historical!F106 -> 4.7 | G106: =Historical!G106 -> 1.6 | H106: =0 -> 0 | I106: =0 -> 0 | J106: =0 -> 0
A107: Purchase of own shares | C107: =Historical!C107 -> -10 | D107: =Historical!D107 -> -11 | E107: =Historical!E107 -> -5 | F107: =Historical!F107 -> -5 | G107: =Historical!G107 -> 0 | H107: =0 -> 0 | I107: =0 -> 0 | J107: =0 -> 0
...

Sheet Drivers
A1: Drivers – forecast assumptions (Session B, 11 Oct 2026)
A2: Blue = assumption. Base case in FY26–FY28 columns; min / max columns are the Monte Carlo ranges (the base value is the most likely point). Reasons are logged in the project plan.
A4: Driver | B4: Unit | C4: FY26 | D4: FY27 | E4: FY28 | F4: FY26 min | G4: FY26 max | H4: FY27 min | I4: FY27 max | J4: FY28 min | K4: FY28 max | L4: Basis
A5: Your decisions (Session B)
A6: Net shop openings | B6: shops | C6: 105 | D6: 110 | E6: 110 | F6: 85 | G6: 112 | H6: 80 | I6: 140 | J6: 80 | K6: 140 | L6: Guidance 100–110; H1 2026 only 34, so more downside
A7: Company-managed share of net openings | B7: % | C7: 0.63 | D7: 0.63 | E7: 0.63 | F7: 0.58 | G7: 0.68 | H7: 0.58 | I7: 0.68 | J7: 0.58 | K7: 0.68 | L7: Rising: 55%, 57%, 60%, 66% (FY22–FY25); revised 11 Oct after FY25 actuals
A8: Company-managed like-for-like growth | B8: % | C8: 0.026 | D8: 0.03 | E8: 0.03 | F8: 0.015 | G8: 0.035 | H8: 0.005 | I8: 0.05 | J8: 0.005 | K8: 0.05 | L8: H1 2026 2.1%, Q3 c.3.4%
A9: New-shop sales vs average mature shop | B9: % | C9: 0.85 | D9: 0.85 | E9: 0.85 | F9: 0.7 | G9: 0.95 | H9: 0.7 | I9: 0.95 | J9: 0.7 | K9: 0.95 | L9: Newer sites are smaller formats and ramp up over time
A10: B2B revenue growth | B10: % | C10: 0.1 | D10: 0.08 | E10: 0.08 | F10: 0.06 | G10: 0.14 | H10: 0.04 | I10: 0.12 | J10: 0.04 | K10: 0.12 | L10: Slowing from 24% to 9%; Tesco Express extension
A11: Underlying operating margin | B11: % | C11: 0.088 | D11: 0.09 | E11: 0.093 | F11: 0.082 | G11: 0.094 | H11: 0.08 | I11: 0.1 | J11: 0.083 | K11: 0.103 | L11: H1 cost ratios improved (partly pay-award timing); H2 Derby +c.£10m; FY28 includes savings
A12: Restructuring total cost | B12: £m | C12: 60 | F12: 45 | G12: 75 | L12: Proposal: c.£60m cash cost (Monte Carlo scales the phasing below)
A13: Restructuring P&L charge phasing (IAS 37, option A) | B13: % of total | C13: 0.75 | D13: 0.16666667 | E13: 0.083333333 | L13: £45m / £10m / £5m at £60m total
A14: Restructuring cash phasing | B14: % of total | C14: 0.16666667 | D14: 0.58333333 | E14: 0.25 | L14: £10m / £35m / £15m at £60m total
A15: Capex (PPE + intangibles) | B15: £m | C15: 180 | D15: 165 | E15: 160 | F15: 170 | G15: 195 | H15: 140 | I15: 200 | J15: 140 | K15: 200 | L15: FY26 guidance £180m; capital intensity falling
A16: Inflation (dividend uplift) | B16: % | C16: 0.02 | D16: 0.02 | E16: 0.02 | L16: Greggs: c.2% LFL cost inflation
A17: Dividend per share declared | B17: £ | C17: =0.69*(1+C16) -> 0.7038 | D17: =C17*(1+D16) -> 0.717876 | E17: =D17*(1+E16) -> 0.73223352 | L17: 69p held in real terms
A18: Tax rate (on profit before tax) | B18: % | C18: 0.26 | D18: 0.26 | E18: 0.26 | F18: 0.255 | G18: 0.27 | H18: 0.255 | I18: 0.27 | J18: 0.255 | K18: 0.27 | L18: Underlying rate 25.7–26.8% vs 25% statutory
A20: Defaults (from FY22–FY25 history, approved in Session B)
A21: Gross margin | B21: % | C21: 0.615 | D21: 0.615 | E21: 0.615 | L21: FY22–FY25 average 61.5%
A22: Administrative costs (underlying) % of revenue | B22: % | C22: 0.047 | D22: 0.047 | E22: 0.047 | L22: FY22–FY25 average 4.7%
A23: Inventory days (of cost of sales) | B23: days | C23: 25 | D23: 25 | E23: 25 | L23: FY22–FY25 average
A24: Receivable days (of revenue) | B24: days | C24: 11.5 | D24: 11.5 | E24: 11.5 | L24: FY22–FY25 average
A25: Payable days (of revenue) | B25: days | C25: 45 | D25: 45 | E25: 45 | L25: FY22–FY25 average
A26: PPE depreciation % of opening PPE | B26: % | C26: 0.135 | D26: 0.135 | E26: 0.135 | L26: Fell from 17.1% to 13.6% as long-life sites added
A27: Intangible capex % of total capex | B27: % | C27: 0.08 | D27: 0.08 | E27: 0.08 | L27: FY25: 7.7%
A28: Amortisation % of opening intangibles | B28: % | C28: 0.18 | D28: 0.18 | E28: 0.18 | L28: FY25: 18.9%
A29: Right-of-use depreciation % of opening ROU assets | B29: % | C29: 0.17 | D29: 0.17 | E29: 0.17 | L29: FY25: 16.8%
A30: Lease interest % of opening lease liability | B30: % | C30: 0.039 | D30: 0.039 | E30: 0.039 | L30: FY24–FY25 c.3.9–4.0%
A31: Interest on cash % of opening cash | B31: % | C31: 0.03 | D31: 0.03 | E31: 0.03 | L31: FY24 4.1%, FY25 1.4% (lower balances)
A32: Interest on borrowings % | B32: % | C32: 0.05 | D32: 0.05 | E32: 0.05 | L32: FY25: c.5% on average drawn
... A35: Current share of lease liabilities | B35: % | C35: 0.139 | D35: 0.139 | E35: 0.139 | L35: FY25: 62.5 / 449.8
A37: Monte Carlo driver links (Session B)
A38: Correlation: LFL growth and operating margin | B38: corr | C38: 0.5 | L38: Moderate
A39: Correlation: LFL growth and B2B growth | B39: corr | C39: 0.3 | L39: Weak
A41: Historical reference (calculated from the Historical tab)
A42: Ratio | C42: FY22 | D42: FY23 | E42: FY24 | F42: FY25
A43: Revenue growth | C43: =Historical!D7/Historical!C7-1 -> 0.23021875 | D43: =Historical!E7/Historical!D7-1 -> 0.19619249 | E43: =Historical!F7/Historical!E7-1 -> 0.11317418 | F43: =Historical!G7/Historical!F7-1 -> 0.067911041
A44: Like-for-like growth | C44: =Historical!D47 -> 0.178 | D44: =Historical!E47 -> 0.137 | E44: =Historical!F47 -> 0.055 | F44: =Historical!G47 -> 0.024
A45: B2B revenue growth | C45: =Historical!D37/Historical!C37-1 -> 0.22053232 | D45: =Historical!E37/Historical!D37-1 -> 0.23800623 | E45: =Historical!F37/Historical!E37-1 -> 0.17111223 | F45: =Historical!G37/Historical!F37-1 -> 0.091534164
A46: Gross margin | C46: =1+Historical!D8/Historical!D7 -> 0.62024061 | D46: =1+Historical!E8/Historical!E7 -> 0.60737179 | E46: =1+Historical!F8/Historical!F7 -> 0.61735504 | F46: =1+Historical!G8/Historical!G7 -> 0.61458721
A47: Underlying operating margin | C47: =Historical!D26 -> 0.1020624 | D47: =Historical!E26 -> 0.094882847 | E47: =Historical!F26 -> 0.096951946 | F47: =Historical!G26 -> 0.087160655
A48: Inventory days | C48: =-Historical!D57/Historical!D8*365 -> 25.794604 | D48: =-Historical!E57/Historical!E8*365 -> 25.069669 | E48: =-Historical!F57/Historical!F8*365 -> 26.139076 | F48: =-Historical!G57/Historical!G8*365 -> 24.521168
A49: Receivable days | C49: =Historical!D58/Historical!D7*365 -> 12.111978 | D49: =Historical!E58/Historical!E7*365 -> 10.851569 | E49: =Historical!F58/Historical!F7*365 -> 11.306593 | F49: =Historical!G58/Historical!G7*365 -> 11.775288
A50: Payable days (of revenue) | C50: =-Historical!D64/Historical!D7*365 -> 46.252314 | D50: =-Historical!E64/Historical!E7*365 -> 42.579299 | E50: =-Historical!F64/Historical!F7*365 -> 44.193556 | F50: =-Historical!G64/Historical!G7*365 -> 46.286724
A51: PPE depreciation % opening PPE | C51: =Historical!D123/Historical!C53 -> 0.16870273 | D51: =Historical!E123/Historical!D53 -> 0.17076923 | E51: =Historical!F123/Historical!E53 -> 0.15010778 | F51: =Historical!G123/Historical!F53 -> 0.13645253
A52: Capex £m | C52: =-Historical!D117 -> 103.3 | D52: =-Historical!E117 -> 198.1 | E52: =-Historical!F117 -> 240.9 | F52: =-Historical!G117 -> 285.4
A54: Latest company guidance and H1 2026 data
A55: H1 2026 sales (£m), 26 weeks to 27 Jun 2026 (H1 2025: 1,027.7) | C55: 1101.5 | L55: H1 2026 presentation, slides 3 and 6
A56: H1 2026 operating profit (£m) (H1 2025: 70.4) | C56: 86.5 | L56: slide 6
A57: H1 2026 company-managed LFL growth | C57: 0.021 | L57: slide 3
A58: Shops trading at 27 Jun 2026 | C58: 2773 | L58: slide 18
A59: FY26 net openings guidance | C59: 100–110 | L59: slide 18
A60: FY26 capex guidance (£m) | C60: 180 | L60: slide 11
A61: FY26 LFL cost inflation expectation | C61: 0.02 | L61: slide 10
A62: H2 2026 extra Derby site costs (£m) | C62: 10 | L62: slide 9

Sheet Scenarios
A1: Scenarios
A2: Phase 3. Fill the yellow cells; the Selected column feeds the Drivers sheet once you link it.
A4: Scenario switch (1 = base, 2 = upside, 3 = downside) | B4: 1 | C4: =CHOOSE(B4,"Base","Upside","Downside") -> Base
A6: Driver (FY26) | B6: Base | C6: Upside | D6: Downside | E6: Selected | F6: Why these values
A7: Company-managed like-for-like growth | E7: =INDEX(B7:D7,1,$B$4) -> 0
A8: Net openings (shops) | E8: =INDEX(B8:D8,1,$B$4) -> 0
A9: Underlying operating margin | E9: =INDEX(B9:D9,1,$B$4) -> 0
A10: Cost inflation (LFL) | E10: =INDEX(B10:D10,1,$B$4) -> 0

Sheet Variance
A1: Variance analysis
A2: Test 1 (Phase 3): forecast FY25 using data up to FY24 only, then compare with actual FY25. Test 2 (Phase 4): locked FY26 forecast vs the January trading update and March results.
A4: Test 1: FY25 back-test
A5: £m | B5: Your FY25 forecast | C5: Actual FY25 | D5: Variance | E5: Variance % | F5: Explanation (one sentence each)
A6: Revenue: company-managed shops | C6: =Historical!G36 -> 1897.2 | D6: =IF(B6="","",C6-B6) | E6: =IF(OR(B6="",B6=0),"",D6/ABS(B6))
A7: Revenue: B2B | C7: =Historical!G37 -> 254 | D7: =IF(B7="","",C7-B7) | E7: =IF(OR(B7="",B7=0),"",D7/ABS(B7))
A8: Total revenue | C8: =Historical!G7 -> 2151.2 | D8: =IF(B8="","",C8-B8) | E8: =IF(OR(B8="",B8=0),"",D8/ABS(B8))
A9: Underlying operating profit | C9: =Historical!G24 -> 187.5 | D9: =IF(B9="","",C9-B9) | E9: =IF(OR(B9="",B9=0),"",D9/ABS(B9))
A10: Underlying profit before tax | C10: =Historical!G25 -> 171.9 | D10: =IF(B10="","",C10-B10) | E10: =IF(OR(B10="",B10=0),"",D10/ABS(B10))
A11: Net cash from operating activities | C11: =Historical!G97 -> 337 | D11: =IF(B11="","",C11-B11) | E11: =IF(OR(B11="",B11=0),"",D11/ABS(B11))
A12: Capex | C12: =Historical!G117 -> -285.4 | D12: =IF(B12="","",C12-B12) | E12: =IF(OR(B12="",B12=0),"",D12/ABS(B12))
A13: Closing cash | C13: =Historical!G61 -> 70.8 | D13: =IF(B13="","",C13-B13) | E13: =IF(OR(B13="",B13=0),"",D13/ABS(B13))
A16: Test 2: FY26 live test (lock your forecast before the January 2027 trading update)
B17: Locked FY26 forecast | C17: Actual (Jan trading update / March results) | D17: Variance | E17: Variance % | F17: Explanation
A18: Total sales (£m) | D18: =IF(OR(B18="",C18=""),"",C18-B18)
A19: Company-managed LFL growth | D19: =IF(OR(B19="",C19=""),"",C19-B19)
A20: Shops at year end | D20: =IF(OR(B20="",C20=""),"",C20-B20)
A21: Underlying PBT (£m, March) | D21: =IF(OR(B21="",C21=""),"",C21-B21)

Sheet Tax & Audit
A1: Tax & Audit review (Phase 3)
A2: Fill the yellow cells from the tax note and the auditor's report. Charges are negative, as on the Historical sheet. Green = linked from Historical. Checks at the bottom of the Checks tab turn on once you start filling.
A4: A. Tax rate reconciliation: why the effective rate differs from the UK rate
A5: £m | B5: Source / note | C5: FY21 | D5: FY22 | E5: FY23 | F5: FY24 | G5: FY25
A6: Profit before tax | B6: Historical | C6: =Historical!C16 -> 145.6 | D6: =Historical!D16 -> 148.3 | E6: =Historical!E16 -> 188.3 | F6: =Historical!F16 -> 203.9 | G6: =Historical!G16 -> 167.4
A7: UK statutory corporation tax rate | B7: Tax note (FY23 note: 23.5%) | C7: 0.19 | D7: 0.19 | E7: 0.235 | F7: 0.25 | G7: 0.25
A8: Tax at the statutory rate | B8: Formula | C8: =-C6*C7 -> -27.664 | D8: =-D6*D7 -> -28.177 | E8: =-E6*E7 -> -44.2505 | F8: =-F6*F7 -> -50.975 | G8: =-G6*G7 -> -41.85
A9: Items not taxable | B9: Tax note: FY24–25 AR25 p153; FY23 AR24 p152; FY22 AR23 p143; FY21 AR22 p132
A10: Non-tax-deductible depreciation
A11: Impact of change in deferred tax rate
A12: Adjustment for prior years
A13: Other (name it in a comment)
A14: Tax charge per reconciliation | B14: Formula | C14: =SUM(C8:C13) -> -27.664 | D14: =SUM(D8:D13) -> -28.177 | E14: =SUM(E8:E13) -> -44.2505 | F14: =SUM(F8:F13) -> -50.975 | G14: =SUM(G8:G13) -> -41.85
A15: Tax charge per income statement | B15: Historical | C15: =Historical!C17 -> -28.1 | D15: =Historical!D17 -> -28 | E15: =Historical!E17 -> -45.8 | F15: =Historical!F17 -> -50.5 | G15: =Historical!G17 -> -45.2
A16: Difference (should be 0 once filled) | B16: Formula | C16: =C14-C15 -> 0.436 | D16: =D14-D15 -> -0.177 | E16: =E14-E15 -> 1.5495 | F16: =F14-F15 -> -0.475 | G16: =G14-G15 -> 3.35
A17: Effective tax rate | B17: Formula | C17: =IF(C6=0,0,-C15/C6) -> 0.19299451 | D17: =IF(D6=0,0,-D15/D6) -> 0.18880647 | E17: =IF(E6=0,0,-E15/E6) -> 0.24322889 | F17: =IF(F6=0,0,-F15/F6) -> 0.24767043 | G17: =IF(G6=0,0,-G15/G6) -> 0.27001195
A18: Gap to statutory rate (percentage points) | B18: Formula: feeds the Drivers adjustment row | C18: =C17-C7 -> 0.0029945055 | D18: =D17-D7 -> -0.0011935266 | E18: =E17-E7 -> 0.0082288901 | F18: =F17-F7 -> -0.0023295733 | G18: =G17-G7 -> 0.020011947
A20: B. Split of the tax charge: current vs deferred
A21: £m | B21: Source / note | C21: FY21 | D21: FY22 | E21: FY23 | F21: FY24 | G21: FY25
A22: Current tax charge | B22: Tax note: FY24–25 AR25 p153; FY23 AR24 p152; FY22 AR23 p143; FY21 AR22 p132
A23: Deferred tax charge | B23: Tax note: FY24–25 AR25 p153; FY23 AR24 p152; FY22 AR23 p143; FY21 AR22 p132
A24: Total (should equal the income statement charge) | B24: Formula | C24: =C22+C23 -> 0 | D24: =D22+D23 -> 0 | E24: =E22+E23 -> 0 | F24: =F22+F23 -> 0 | G24: =G22+G23 -> 0
A25: Difference | B25: Formula | C25: =C24-Historical!C17 -> 28.1 | D25: =D24-Historical!D17 -> 28 | E25: =E24-Historical!E17 -> 45.8 | F25: =F24-Historical!F17 -> 50.5 | G25: =G24-Historical!G17 -> 45.2
A26: Memo: tax actually paid in cash | B26: Historical (cash flow) | C26: =Historical!C93 -> -19.2 | D26: =Historical!D93 -> -13.3 | E26: =Historical!E93 -> -11.9 | F26: =Historical!F93 -> -27.7 | G26: =Historical!G93 -> -31.5
A28: C. Deferred tax liability roll-forward (shown as positive balances)
A29: £m | B29: Source / note | C29: FY21 | D29: FY22 | E29: FY23 | F29: FY24 | G29: FY25
A30: Opening deferred tax liability | B30: FY21: prior-year balance from AR22 p111 (FY20 column of AR21) | D30: =C34 -> 0 | E30: =D34 -> 0 | F30: =E34 -> 0 | G30: =F34 -> 0
A31: Charged to the income statement | B31: Deferred tax note
A32: Charged to other comprehensive income | B32: Deferred tax note
A33: Other movements | B33: Deferred tax note
A34: Closing liability (calculated) | B34: Formula | C34: =SUM(C30:C33) -> 0 | D34: =SUM(D30:D33) -> 0 | E34: =SUM(E30:E33) -> 0 | F34: =SUM(F30:F33) -> 0 | G34: =SUM(G30:G33) -> 0
A35: Closing liability per balance sheet | B35: Historical | C35: =-Historical!C72 -> 10 | D35: =-Historical!D72 -> 26.3 | E35: =-Historical!E72 -> 54.7 | F35: =-Historical!F72 -> 72.6 | G35: =-Historical!G72 -> 93.7
A36: Difference (should be 0 once filled) | B36: Formula | C36: =C34-C35 -> -10 | D36: =D34-D35 -> -26.3 | E36: =E34-E35 -> -54.7 | F36: =F34-F35 -> -72.6 | G36: =G34-G35 -> -93.7
A38: Memo: capex (PPE + intangibles, cash) | B38: Historical | C38: =-Historical!C117 -> 54.3 | D38: =-Historical!D117 -> 103.3 | E38: =-Historical!E117 -> 198.1 | F38: =-Historical!F117 -> 240.9 | G38: =-Historical!G117 -> 285.4
A39: Memo: depreciation of PPE + amortisation | B39: Historical | C39: =Historical!C123+Historical!C122 -> 58.7 | D39: =Historical!D123+Historical!D122 -> 62.7 | E39: =Historical!E123+Historical!E122 -> 70.5 | F39: =Historical!F123+Historical!F122 -> 80.8 | G39: =Historical!G123+Historical!G122 -> 95.4
A40: Capex in excess of depreciation | B40: Formula | C40: =C38-C39 -> -4.4 | D40: =D38-D39 -> 40.6 | E40: =E38-E39 -> 127.6 | F40: =F38-F39 -> 160.1 | G40: =G38-G39 -> 190
A43: D. Key audit matters (AR25 independent auditor's report, PDF pp. 123–125) mapped to the model
A44: Key audit matter | B44: What the auditor did (in brief) | C44: Model lines affected and how I treated them
A50: Example of the level of detail (replace with your own, from the report): Impairment of shop assets | Tested the value-in-use model and its assumptions | Right-of-use assets and PPE; impairment kept inside underlying costs, see Notes
A52: E. Controls in my model (how I know the numbers are right)
A53: Control 1
A54: Control 2
A55: Control 3
A56: Ideas: source page for every typed figure; Checks tab ties totals to the reports; balance and cash checks on every forecast year; colour coding of inputs vs formulas.

Sheet Checks
A1: Checks – every row should show 0 (green). Red means something does not tie.
A2: Historical checks work now. FY26–FY28 checks read 0 while the forecast is empty; they only mean something once you have built it.
A4: Check | B4: Sheet | C4: FY21 | D4: FY22 | E4: FY23 | F4: FY24 | G4: FY25 | H4: FY26 | I4: FY27 | J4: FY28
A5: Operating profit ties to report | B5: Historical | C5: =ROUND(Historical!C13-Historical!C30,1) -> 0 | D5: =ROUND(Historical!D13-Historical!D30,1) -> 0 | E5: =ROUND(Historical!E13-Historical!E30,1) -> 0 | F5: =ROUND(Historical!F13-Historical!F30,1) -> 0 | G5: =ROUND(Historical!G13-Historical!G30,1) -> 0
A6: Profit before tax ties to report | B6: Historical | C6: =ROUND(Historical!C16-Historical!C31,1) -> 0 | D6: =ROUND(Historical!D16-Historical!D31,1) -> 0 | E6: =ROUND(Historical!E16-Historical!E31,1) -> 0 | F6: =ROUND(Historical!F16-Historical!F31,1) -> 0 | G6: =ROUND(Historical!G16-Historical!G31,1) -> 0
A7: Profit for the year ties to report | B7: Historical | C7: =ROUND(Historical!C18-Historical!C32,1) -> 0 | D7: =ROUND(Historical!D18-Historical!D32,1) -> 0 | E7: =ROUND(Historical!E18-Historical!E32,1) -> 0 | F7: =ROUND(Historical!F18-Historical!F32,1) -> 0 | G7: =ROUND(Historical!G18-Historical!G32,1) -> 0
A8: Underlying PBT ties to ten-year history | B8: Historical | C8: =ROUND(Historical!C25-Historical!C33,1) -> 0 | D8: =ROUND(Historical!D25-Historical!D33,1) -> 0 | E8: =ROUND(Historical!E25-Historical!E33,1) -> 0 | F8: =ROUND(Historical!F25-Historical!F33,1) -> 0 | G8: =ROUND(Historical!G25-Historical!G33,1) -> 0
A9: Revenue split ties to total revenue | B9: Historical | C9: =ROUND(Historical!C36+Historical!C37-Historical!C7,1) -> 0 | D9: =ROUND(Historical!D36+Historical!D37-Historical!D7,1) -> 0 | E9: =ROUND(Historical!E36+Historical!E37-Historical!E7,1) -> 0 | F9: =ROUND(Historical!F36+Historical!F37-Historical!F7,1) -> 0 | G9: =ROUND(Historical!G36+Historical!G37-Historical!G7,1) -> 0
A10: Total assets tie to report | B10: Historical | C10: =ROUND(Historical!C63-Historical!C83,1) -> 0 | D10: =ROUND(Historical!D63-Historical!D83,1) -> 0 | E10: =ROUND(Historical!E63-Historical!E83,1) -> 0 | F10: =ROUND(Historical!F63-Historical!F83,1) -> 0 | G10: =ROUND(Historical!G63-Historical!G83,1) -> 0
A11: Net assets tie to report | B11: Historical | C11: =ROUND(Historical!C77-Historical!C84,1) -> 0 | D11: =ROUND(Historical!D77-Historical!D84,1) -> 0 | E11: =ROUND(Historical!E77-Historical!E84,1) -> 0 | F11: =ROUND(Historical!F77-Historical!F84,1) -> 0 | G11: =ROUND(Historical!G77-Historical!G84,1) -> 0
A12: Balance sheet balances (net assets less equity) | B12: Historical + Forecast | C12: =ROUND(Historical!C77-Historical!C82,1) -> 0 | D12: =ROUND(Historical!D77-Historical!D82,1) -> 0 | E12: =ROUND(Historical!E77-Historical!E82,1) -> 0 | F12: =ROUND(Historical!F77-Historical!F82,1) -> 0 | G12: =ROUND(Historical!G77-Historical!G82,1) -> 0 | H12: =ROUND(Forecast!H77-Forecast!H82,1) -> 0 | I12: =ROUND(Forecast!I77-Forecast!I82,1) -> 0 | J12: =ROUND(Forecast!J77-Forecast!J82,1) -> 0
A13: Cash flow closing cash equals balance sheet cash | B13: Historical + Forecast | C13: =ROUND(Historical!C113-Historical!C61,1) -> 0 | D13: =ROUND(Historical!D113-Historical!D61,1) -> 0 | E13: =ROUND(Historical!E113-Historical!E61,1) -> 0 | F13: =ROUND(Historical!F113-Historical!F61,1) -> 0 | G13: =ROUND(Historical!G113-Historical!G61,1) -> 0 | H13: =ROUND(Forecast!H113-Forecast!H61,1) -> 0 | I13: =ROUND(Forecast!I113-Forecast!I61,1) -> 0 | J13: =ROUND(Forecast!J113-Forecast!J61,1) -> 0
A14: Net change in cash ties to report | B14: Historical | C14: =ROUND(Historical!C111-Historical!C114,1) -> 0 | D14: =ROUND(Historical!D111-Historical!D114,1) -> 0 | E14: =ROUND(Historical!E111-Historical!E114,1) -> 0 | F14: =ROUND(Historical!F111-Historical!F114,1) -> 0 | G14: =ROUND(Historical!G111-Historical!G114,1) -> 0
A15: Cash generated from operations: note ties to statement | B15: Historical | C15: =ROUND(Historical!C138-Historical!C92,1) -> 0 | D15: =ROUND(Historical!D138-Historical!D92,1) -> 0 | E15: =ROUND(Historical!E138-Historical!E92,1) -> 0 | F15: =ROUND(Historical!F138-Historical!F92,1) -> 0 | G15: =ROUND(Historical!G138-Historical!G92,1) -> 0
A16: Profit in cash flow note equals income statement | B16: Historical | C16: =ROUND(Historical!C121-Historical!C18,1) -> 0 | D16: =ROUND(Historical!D121-Historical!D18,1) -> 0 | E16: =ROUND(Historical!E121-Historical!E18,1) -> 0 | F16: =ROUND(Historical!F121-Historical!F18,1) -> 0 | G16: =ROUND(Historical!G121-Historical!G18,1) -> 0
A17: Shop openings less closures equal net openings | B17: Historical | C17: =ROUND(Historical!C46,1) -> 0 | D17: =ROUND(Historical!D46,1) -> 0 | E17: =ROUND(Historical!E46,1) -> 0 | F17: =ROUND(Historical!F46,1) -> 0 | G17: =ROUND(Historical!G46,1) -> 0
A19: Total of absolute differences (historical) | C19: =SUMPRODUCT(ABS(C5:G17)) -> 0
A20: Overall status (historical) | C20: =IF(C19<0.05,"OK","CHECK") -> OK
A22: Phase 3 checks (Tax & Audit tab): blank until you start filling that section
A23: Tax reconciliation ties to income statement charge | B23: Tax & Audit | C23: =IF(COUNT('Tax & Audit'!C9:C13)=0,"",ROUND('Tax & Audit'!C16,1)) | D23: =IF(COUNT('Tax & Audit'!D9:D13)=0,"",ROUND('Tax & Audit'!D16,1)) | E23: =IF(COUNT('Tax & Audit'!E9:E13)=0,"",ROUND('Tax & Audit'!E16,1)) | F23: =IF(COUNT('Tax & Audit'!F9:F13)=0,"",ROUND('Tax & Audit'!F16,1)) | G23: =IF(COUNT('Tax & Audit'!G9:G13)=0,"",ROUND('Tax & Audit'!G16,1))
A24: Current + deferred tax equals income statement charge | B24: Tax & Audit | C24: =IF(COUNT('Tax & Audit'!C22:C23)=0,"",ROUND('Tax & Audit'!C25,1)) | D24: =IF(COUNT('Tax & Audit'!D22:D23)=0,"",ROUND('Tax & Audit'!D25,1)) | E24: =IF(COUNT('Tax & Audit'!E22:E23)=0,"",ROUND('Tax & Audit'!E25,1)) | F24: =IF(COUNT('Tax & Audit'!F22:F23)=0,"",ROUND('Tax & Audit'!F25,1)) | G24: =IF(COUNT('Tax & Audit'!G22:G23)=0,"",ROUND('Tax & Audit'!G25,1))
A25: Deferred tax roll-forward ties to balance sheet | B25: Tax & Audit | C25: =IF(COUNT('Tax & Audit'!C31:C33)=0,"",ROUND('Tax & Audit'!C36,1)) | D25: =IF(COUNT('Tax & Audit'!D31:D33)=0,"",ROUND('Tax & Audit'!D36,1)) | E25: =IF(COUNT('Tax & Audit'!E31:E33)=0,"",ROUND('Tax & Audit'!E36,1)) | F25: =IF(COUNT('Tax & Audit'!F31:F33)=0,"",ROUND('Tax & Audit'!F36,1)) | G25: =IF(COUNT('Tax & Audit'!G31:G33)=0,"",ROUND('Tax & Audit'!G36,1))
A28: Your verification log (Phase 1): tick when you have checked each block against the PDF
A29: Block | B29: Checked by you (Y/N) | C29: Date | D29: Notes
A30: Income statement FY21–FY25
A31: Exceptional items
A32: Revenue split and shop KPIs
A33: Balance sheet FY21–FY25
A34: Cash flow FY21–FY25
A35: Cash generated from operations note

Sheet Summary
A1: Summary (Phase 3) – one page you could show an interviewer
A3: 1. What Greggs does and why I chose it (2–3 lines)
A7: 2. Key assumptions (base case) and why
A11: 3. Base case outputs: revenue, underlying operating profit, PBT, free cash flow, FY26–FY28
A15: 4. Scenario range: upside and downside FY26 PBT
A19: 5. Sensitivities: +/-1 point LFL growth and +/-1 point operating margin on FY26 PBT
A23: 6. Back-test result: FY25 forecast vs actual, and what I learned
A27: 7. Main simplifications and where the model would break
A31: 8. Tax and audit points: why the tax rate rose, deferred tax, key audit matters and how the model handles them
